{"data":{"symbol":"eatv","holdings":[{"symbol":"MKC","name":"McCormick & Co Inc Registered Shs Non Vt...","percent":7.32},{"symbol":"--","name":"GEA Group AG","percent":7.23},{"symbol":"--","name":"Tate & Lyle PLC","percent":6.3},{"symbol":"FDP","name":"Fresh Del Monte Produce Inc","percent":5.91},{"symbol":"DOLE","name":"Dole PLC","percent":5.6},{"symbol":"INGR","name":"Ingredion Inc","percent":4.14},{"symbol":"--","name":"Kubota Corp","percent":4.1},{"symbol":"XYL","name":"Xylem Inc","percent":4.04},{"symbol":"--","name":"Givaudan SA","percent":3.98},{"symbol":"SENEA","name":"Seneca Foods Corp Class A","percent":3.71},{"symbol":"--","name":"SIG Group AG Ordinary Shares","percent":3.49},{"symbol":"--","name":"Vitasoy International Holdings Ltd","percent":3.47},{"symbol":"TAP","name":"Molson Coors Beverage Co Shs -B- Non-Vot...","percent":3.35},{"symbol":"CNH","name":"CNH Industrial NV","percent":3.13},{"symbol":"BUD","name":"Anheuser-Busch InBev SA/NV ADR","percent":3.08},{"symbol":"--","name":"Novonesis (Novozymes) B Class B","percent":3.03},{"symbol":"--","name":"DSM Firmenich AG","percent":3.03},{"symbol":"FGXXX","name":"First American Government Obligs X","percent":2.59},{"symbol":"--","name":"Corbion NV","percent":2.38},{"symbol":"USFR","name":"WisdomTree Floating Rate Treasury ETF","percent":2.22},{"symbol":"COCO","name":"The Vita Coco Co Inc","percent":2.01},{"symbol":"IFF","name":"International Flavors & Fragrances Inc","percent":1.9},{"symbol":"ONON","name":"On Holding AG","percent":1.88},{"symbol":"SXT","name":"Sensient Technologies Corp","percent":1.56},{"symbol":"--","name":"Lenzing AG","percent":1.56},{"symbol":"--","name":"Evonik Industries AG","percent":1.51},{"symbol":"--","name":"Agronomics Ltd","percent":1.31},{"symbol":"ELF","name":"e.l.f. Beauty Inc","percent":1.23},{"symbol":"LMNR","name":"Limoneira Co","percent":0.74},{"symbol":"--","name":"Ultrafabrics Holdings Co Ltd","percent":0.64},{"symbol":"CROX","name":"Crocs Inc","percent":0.59},{"symbol":"LSF","name":"Laird Superfood Inc Ordinary Shares","percent":0.53},{"symbol":"MGPI","name":"MGP Ingredients Inc","percent":0.49},{"symbol":"AVO","name":"Mission Produce Inc Ordinary Shares","percent":0.35},{"symbol":"OTLY","name":"Oatly Group AB ADR","percent":0.26},{"symbol":"--","name":"SunOpta Inc","percent":0.24},{"symbol":"LW","name":"Lamb Weston Holdings Inc","percent":0.22},{"symbol":"--","name":"Valsoia SpA","percent":0.18},{"symbol":"--","name":"DEPOSITS WITH BROKER FOR SHORT POSITIONS","percent":0.18},{"symbol":"BYND","name":"Beyond Meat Inc","percent":0.17},{"symbol":"CELH","name":"Celsius Holdings Inc","percent":0.13},{"symbol":"VFF","name":"Village Farms International Inc","percent":0.12},{"symbol":"--","name":"Lassonde Industries Inc Shs -A- Subord V...","percent":0.06},{"symbol":"--","name":"DANISH KRONE","percent":0.02}],"name":"VegTech Food Innovation & Climate"},"expiresAt":1744405146069}